mseep_pdf2zh-1.9.11.dist-info/licenses/LICENSE
pdf2zh/__init__.py
pdf2zh/backend.py
pdf2zh/cache.py
pdf2zh/config.py
pdf2zh/converter.py
pdf2zh/doclayout.py
pdf2zh/gui.py
pdf2zh/high_level.py
pdf2zh/mcp_server.py
pdf2zh/pdf2zh.py
pdf2zh/pdfinterp.py
pdf2zh/translator.py
mseep_pdf2zh-1.9.11.dist-info/METADATA
mseep_pdf2zh-1.9.11.dist-info/WHEEL
mseep_pdf2zh-1.9.11.dist-info/top_level.txt
mseep_pdf2zh-1.9.11.dist-info/RECORD
