Metadata-Version: 2.4
Name: mseep-pdf2zh
Version: 1.9.11
Summary: Latex PDF Translator
Home-page: https://github.com/mseep
Author: mseep
Author-email: support@skydeck.ai
Maintainer: mseep
Maintainer-email: support@skydeck.ai
Keywords: mseep
Classifier: Programming Language :: Python :: 3
Classifier: License :: OSI Approved :: MIT License
Classifier: Operating System :: OS Independent
Requires-Python: >=3.6
License-File: LICENSE
Requires-Dist: requests
Requires-Dist: pymupdf<1.25.3
Requires-Dist: tqdm
Requires-Dist: tenacity
Requires-Dist: numpy
Requires-Dist: ollama
Requires-Dist: xinference-client
Requires-Dist: deepl
Requires-Dist: openai>=1.0.0
Requires-Dist: azure-ai-translation-text<=1.0.1
Requires-Dist: gradio<5.36
Requires-Dist: huggingface_hub
Requires-Dist: onnx
Requires-Dist: onnxruntime
Requires-Dist: opencv-python-headless
Requires-Dist: tencentcloud-sdk-python-tmt
Requires-Dist: pdfminer-six==20250416
Requires-Dist: gradio_pdf>=0.0.21
Requires-Dist: pikepdf
Requires-Dist: peewee>=3.17.8
Requires-Dist: fontTools
Requires-Dist: babeldoc<0.3.0,>=0.1.22
Requires-Dist: rich
Dynamic: author
Dynamic: author-email
Dynamic: classifier
Dynamic: description
Dynamic: description-content-type
Dynamic: home-page
Dynamic: keywords
Dynamic: license-file
Dynamic: maintainer
Dynamic: maintainer-email
Dynamic: requires-dist
Dynamic: requires-python
Dynamic: summary
